[
    {
        "id": 1,
        "imgsrc": "img/show3.jpg",
        "name": "Mega Matine Bailable",
        "date": "25/05/22",
        "time": "20:00",
        "tickets": 600,
        "price": 1000
    },
    {
        "id": 3,
        "imgsrc": "img/show5.jpg",
        "name": "Kolombo en UMMA",
        "date": "10/06/22",
        "time": "21:00",
        "tickets": 550,
        "price": 800
    },
    {
        "id": 2,
        "imgsrc": "img/show4.jpg",
        "name": "Show Matías Valdez",
        "date": "28/05/22",
        "time": "22:00",
        "tickets": 550,
        "price": 750
    },
    {
        "id": 4,
        "imgsrc": "img/show6.jpg",
        "name": "Noche Retro en UMMA",
        "date": "11/06/22",
        "time": "21:00",
        "tickets": 550,
        "price": 800
    },
    {
        "id": 5,
        "imgsrc": "img/show7.jpg",
        "name": "Los Hijos de los Barrios",
        "date": "18/06/22",
        "time": "21:00",
        "tickets": 350,
        "price": 750
    },
    {
        "id": 6,
        "imgsrc": "img/show8.jpg",
        "name": "Atómicos: Tributo a Divididos",
        "date": "19/06/22",
        "time": "22:00",
        "tickets": 350,
        "price": 1000
    },
    {
        "id": 7,
        "imgsrc": "img/show9.jpg",
        "name": "NTVG en UMMA",
        "date": "07/07/22",
        "time": "21:00",
        "tickets": 550,
        "price": 800
    },
    {
        "id": 8,
        "imgsrc": "img/show10.jpg",
        "name": "Charla del 'Pela' Romero",
        "date": "07/07/22",
        "time": "21:30",
        "tickets": 350,
        "price": 750
    },
    {
        "id": 9,
        "imgsrc": "img/show11.jpg",
        "name": "Un Show de Otro Planeta",
        "date": "16/07/22",
        "time": "16:30",
        "tickets": 1200,
        "price": 500
    },
    {
        "id": 10,
        "imgsrc": "img/show12.jpg",
        "name": "Las Manos de Filippi",
        "date": "03/09/22",
        "time": "21:00",
        "tickets": 550,
        "price": 750
    }
]